pyacryl2/__init__.py
pyacryl2/async_client.py
pyacryl2/client.py
pyacryl2/utils/__init__.py
pyacryl2/utils/address.py
pyacryl2/utils/address_generator.py
pyacryl2/utils/async_address.py
pyacryl2/utils/crypto.py
wavespy/__init__.py
wavespy/async_client.py
wavespy/client.py
wavespy/utils/__init__.py
wavespy/utils/address.py
wavespy/utils/address_generator.py
wavespy/utils/async_address.py
wavespy/utils/crypto.py
wavespy-0.1.dist-info/LICENSE
wavespy-0.1.dist-info/METADATA
wavespy-0.1.dist-info/WHEEL
wavespy-0.1.dist-info/top_level.txt
wavespy-0.1.dist-info/RECORD
