Metadata-Version: 2.1
Name: wavespy
Version: 0.1
Summary: Waves node API client
Home-page: https://github.com/DPInvaders/wavespy
Author: DPInvaders
Author-email: dp@theinvaders.pro
License: MIT
Keywords: waves wavespy api client async
Platform: UNKNOWN
Classifier: Intended Audience :: Developers
Classifier: License :: OSI Approved :: MIT License
Classifier: Operating System :: OS Independent
Classifier: Programming Language :: Python :: 3.6
Classifier: Programming Language :: Python :: 3.7
Classifier: Programming Language :: Python
Classifier: Topic :: Software Development :: Libraries :: Python Modules
Requires-Dist: aiohttp (==3.5.4)
Requires-Dist: base58 (==1.0.3)
Requires-Dist: mnemonic (==0.18)
Requires-Dist: pysha3 (==1.0.2)
Requires-Dist: python-axolotl-curve25519 (==0.4.1.post2)
Requires-Dist: requests (==2.21.0)
Requires-Dist: ujson (==1.35)
